enki_sr/__init__.py
enki_sr/enki.py
enki_sr-0.1.4.dist-info/entry_points.txt
enki_sr-0.1.4.dist-info/WHEEL
enki_sr-0.1.4.dist-info/METADATA
enki_sr-0.1.4.dist-info/RECORD
