Metadata-Version: 2.1
Name: enki-sr
Version: 0.1.4
Summary: 
Author: Marcus Orochena
Author-email: marcus.orochena@gmail.com
Requires-Python: >=3.9,<4.0
Classifier: Programming Language :: Python :: 3
Classifier: Programming Language :: Python :: 3.10
Classifier: Programming Language :: Python :: 3.9
Requires-Dist: blessed (>=1.19.1,<2.0.0)
Requires-Dist: typer (>=0.6.1,<0.7.0)
